eigenapi_client/Client.py
eigenapi_client/__init__.py
eigenapi_client/endpoints/LatestBlockApi.py
eigenapi_client/endpoints/PoolSandwichedApi.py
eigenapi_client/endpoints/StatusApi.py
eigenapi_client/endpoints/TransactionApi.py
eigenapi_client/endpoints/Websocket.py
eigenapi_client/endpoints/__init__.py
eigenapi_client/endpoints/schema.py
eigenapi_client-0.2.1.dist-info/METADATA
eigenapi_client-0.2.1.dist-info/WHEEL
eigenapi_client-0.2.1.dist-info/top_level.txt
eigenapi_client-0.2.1.dist-info/RECORD
