Metadata-Version: 2.1
Name: eigenapi-client
Version: 0.2.1
Summary: EigenAPI Client
Home-page: https://github.com/eigenphi/eigenapi-client
Author: David
Author-email: david@eigenphi.com
License: MIT
Classifier: Environment :: Web Environment
Classifier: Intended Audience :: Developers
Classifier: Operating System :: OS Independent
Classifier: Topic :: Text Processing :: Indexing
Classifier: Topic :: Utilities
Classifier: Topic :: Internet
Classifier: Topic :: Software Development :: Libraries :: Python Modules
Classifier: Programming Language :: Python
Classifier: Programming Language :: Python :: 3
Classifier: Programming Language :: Python :: 3.6
Requires-Dist: setuptools (>=60.8.3)
Requires-Dist: wheel (==0.36.2)
Requires-Dist: requests (==2.24.0)
Requires-Dist: websockets (==10.4)
